README.md
setup.py
taza/__init__.py
taza/query.py
taza.egg-info/PKG-INFO
taza.egg-info/SOURCES.txt
taza.egg-info/dependency_links.txt
taza.egg-info/top_level.txt
taza/tacyt/ExternalApiCompareRequest.py
taza/tacyt/ExternalApiFilterRequest.py
taza/tacyt/ExternalApiSearchRequest.py
taza/tacyt/ExternalApiTagRequest.py
taza/tacyt/Filter.py
taza/tacyt/TacytApp.py
taza/tacyt/Version.py
taza/tacyt/__init__.py
taza/tacyt/authorization/Auth.py
taza/tacyt/authorization/Error.py
taza/tacyt/authorization/Response.py
taza/tacyt/authorization/__init__.py