Metadata-Version: 1.0
Name: taza
Version: 2.0.0
Summary: A set of classes and abstractions for working with Tacyt
Home-page: https://gitlab.software.imdea.org/android/taza
Author: Daniel Domínguez
Author-email: daniel.dominguez@imdea.org
License: MIT
Keywords: mobile tacyt android
Platform: UNKNOWN
